linger/__init__.py
linger/__version.py
linger/config.py
linger/conv_bn_fuser.py
linger/dumper.py
linger/initialize.py
linger/layer_normalizer.py
linger/layer_tracer.py
linger/quant.py
linger/utils.py
linger/lib/lingerext.cpython-36m-x86_64-linux-gnu.so
linger/lib/lingerext.cpython-37m-x86_64-linux-gnu.so
linger/lib/lingerext.cpython-38-x86_64-linux-gnu.so
linger/modules/__init__.py
linger/modules/modules_configs.py
linger/modules/normalize_batchnorm2d.py
linger/modules/normalize_conv1d.py
linger/modules/normalize_conv2d.py
linger/modules/normalize_convTranspose2d.py
linger/modules/normalize_convTransposebn2d.py
linger/modules/normalize_convbn1d.py
linger/modules/normalize_convbn2d.py
linger/modules/normalize_embedding.py
linger/modules/normalize_fastGRU.py
linger/modules/normalize_fastLSTM.py
linger/modules/normalize_layernorm.py
linger/modules/normalize_linear.py
linger/onnx/__init__.py
linger/onnx/export.py
linger/onnx/infer_type.py
linger/onnx/scope.py
linger/onnx/update_dequant.py
linger/ops/__init__.py
linger/ops/avgpool2d_int.py
linger/ops/batchnorm_int.py
linger/ops/bmm_int.py
linger/ops/conv1d_int.py
linger/ops/conv_int.py
linger/ops/convtranspose_int.py
linger/ops/embedding_int.py
linger/ops/gru_int.py
linger/ops/iqtensor.py
linger/ops/layernorm_int.py
linger/ops/linear_int.py
linger/ops/linger_functional.py
linger/ops/lstm_int.py
linger/ops/module_self.py
linger/ops/ops.py
linger/ops/ops_configs.py
linger/ops/ops_names.py
linger/ops/relu6_int.py
linger/ops/requant.py
linger/ops/scaledround_int.py
linger/ops/shuffle_channel.py
linger/tools/__init__.py
linger/tools/fix_dequant.py
linger/tools/weight_bias_analyse.py
linger/tools/onnx_quant/__init__.py
linger/tools/onnx_quant/fix_quant_onnx_replace.py
linger/tools/onnx_quant/transform/__init__.py
linger/tools/onnx_quant/transform/onnx_utils.py
linger/tools/onnx_quant/transform/replace_add.py
linger/tools/onnx_quant/transform/replace_avgpoolint.py
linger/tools/onnx_quant/transform/replace_clip.py
pylinger-1.1.1.dist-info/LICENSE
pylinger-1.1.1.dist-info/METADATA
pylinger-1.1.1.dist-info/WHEEL
pylinger-1.1.1.dist-info/top_level.txt
pylinger-1.1.1.dist-info/RECORD
