Metadata-Version: 2.1
Name: pylinger
Version: 1.1.1
Summary: linger is package of fix training
Home-page: https://github.com/LISTENAI/linger
Author: listenai
Author-email: lingerthinker@listenai.com
Classifier: Intended Audience :: Science/Research
Classifier: Topic :: Scientific/Engineering
Classifier: Topic :: Scientific/Engineering :: Mathematics
Classifier: Topic :: Scientific/Engineering :: Artificial Intelligence
Classifier: Topic :: Software Development
Classifier: Topic :: Software Development :: Libraries
Classifier: Topic :: Software Development :: Libraries :: Python Modules
Classifier: Programming Language :: C++
Classifier: Programming Language :: Python :: 3
License-File: LICENSE
